synapse/__init__.py
synapse/index.py
synapse_fm-0.0.6.dist-info/LICENSE
synapse_fm-0.0.6.dist-info/METADATA
synapse_fm-0.0.6.dist-info/WHEEL
synapse_fm-0.0.6.dist-info/entry_points.txt
synapse_fm-0.0.6.dist-info/top_level.txt
synapse_fm-0.0.6.dist-info/RECORD
