Metadata-Version: 2.1
Name: synapse-fm
Version: 0.0.6
Summary: Introducing Synapse, a terminal-based file manager that simplifies and streamlines file management tasks from the command line. Built using Python's curses module, Synapse has a user-friendly interface and features like file preview, directory and file information, formatting for various file types, and support for symbolic links. Whether you're a casual or power user, Synapse has the functionality you need. Try Synapse today!
Author-email: Eyetu Kingsley <eyetukingsley330@gmail.com>
Project-URL: Github Repository, https://github.com/CodeKing12/synapse
Project-URL: Bug Tracker, https://github.com/CodeKing12/synapse/issues
Classifier: Programming Language :: Python :: 3
Classifier: License :: OSI Approved :: GNU General Public License v3 (GPLv3)
Classifier: Operating System :: Unix
Requires-Python: >=3.6
License-File: LICENSE
